innvestigate/__init__.py
innvestigate/analyzer/__init__.py
innvestigate/analyzer/base.py
innvestigate/analyzer/deeptaylor.py
innvestigate/analyzer/gradient_based.py
innvestigate/analyzer/misc.py
innvestigate/analyzer/network_base.py
innvestigate/analyzer/relevance_based/__init__.py
innvestigate/analyzer/relevance_based/relevance_analyzer.py
innvestigate/analyzer/relevance_based/relevance_rule.py
innvestigate/analyzer/relevance_based/utils.py
innvestigate/analyzer/reverse_base.py
innvestigate/analyzer/wrapper.py
innvestigate/backend/__init__.py
innvestigate/backend/checks.py
innvestigate/backend/graph.py
innvestigate/backend/types.py
innvestigate/layers.py
innvestigate/tools/__init__.py
innvestigate/tools/perturbate.py
innvestigate/utils/__init__.py
innvestigate/utils/sequence.py
innvestigate/utils/visualizations.py
innvestigate-2.1.2.dist-info/LICENSE
innvestigate-2.1.2.dist-info/METADATA
innvestigate-2.1.2.dist-info/WHEEL
innvestigate-2.1.2.dist-info/RECORD
