Metadata-Version: 2.1
Name: innvestigate
Version: 2.1.2
Summary: A toolbox to innvestigate neural networks' predictions.
Home-page: https://github.com/albermax/innvestigate
License: BSD-2-Clause
Keywords: XAI,LRP,Deep Taylor
Author: Maxmilian Alber
Author-email: workDoTalberDoTmaximilian@gmail.com
Maintainer: Adrian Hill
Maintainer-email: hill@tu-berlin.de
Requires-Python: >=3.9,<3.12
Classifier: Development Status :: 5 - Production/Stable
Classifier: Environment :: Console
Classifier: Intended Audience :: Science/Research
Classifier: License :: OSI Approved :: BSD License
Classifier: Operating System :: POSIX :: Linux
Classifier: Programming Language :: Python :: 3
Classifier: Programming Language :: Python :: 3.9
Classifier: Programming Language :: Python :: 3.10
Classifier: Programming Language :: Python :: 3.11
Classifier: Programming Language :: Python :: 3.8
Classifier: Topic :: Scientific/Engineering :: Artificial Intelligence
Requires-Dist: future (>=0.18,<0.19)
Requires-Dist: matplotlib (>=3.5,<4)
Requires-Dist: numpy (>=1.22,<2)
Requires-Dist: tensorflow (>=2.6,<2.15)
Project-URL: Documentation, https://innvestigate.readthedocs.io/en/latest/
Project-URL: Repository, https://github.com/albermax/innvestigate
